survey_dashboard/__init__.py
survey_dashboard/analysis.py
survey_dashboard/data/display_specifications/hcs_clean_dictionaries.py
survey_dashboard/data/display_specifications/hmc_colordicts.py
survey_dashboard/data/display_specifications/hmc_custom_layout.py
survey_dashboard/data/download_data.py
survey_dashboard/data/generate_overview.py
survey_dashboard/data/germany_map.svg
survey_dashboard/data/hmc_repos.json
survey_dashboard/description.html
survey_dashboard/devel_plots.ipynb
survey_dashboard/main.py
survey_dashboard/plots.py
survey_dashboard/survey_dashboard.ipynb
survey_dashboard/text_display.py
survey_dashboard-0.1.0.dist-info/LICENSE
survey_dashboard-0.1.0.dist-info/METADATA
survey_dashboard-0.1.0.dist-info/WHEEL
survey_dashboard-0.1.0.dist-info/RECORD
