Metadata-Version: 2.1
Name: survey-dashboard
Version: 0.1.0
Summary: A Dashboard displaying survey data in an interactive way and allow for interactive exploration.
License: MIT
Keywords: dashboard,data visualization,survey data,categorical data,interactive visualization,bokeh,panel
Author: Jens Broeder
Author-email: j.broeder@fz-juelich.de
Requires-Python: >=3.8,<4.0
Classifier: Development Status :: 5 - Production/Stable
Classifier: Intended Audience :: Information Technology
Classifier: Intended Audience :: Science/Research
Classifier: License :: OSI Approved :: MIT License
Classifier: Natural Language :: English
Classifier: Operating System :: MacOS :: MacOS X
Classifier: Operating System :: POSIX :: Linux
Classifier: Programming Language :: Python
Classifier: Programming Language :: Python :: 3
Classifier: Programming Language :: Python :: 3.8
Classifier: Programming Language :: Python :: 3.9
Classifier: Programming Language :: Python :: 3.10
Classifier: Programming Language :: Python :: 3.11
Classifier: Programming Language :: Python :: 3.12
Classifier: Topic :: Database :: Front-Ends
Classifier: Topic :: Education
Classifier: Topic :: Scientific/Engineering
Classifier: Topic :: Scientific/Engineering :: Information Analysis
Classifier: Topic :: Scientific/Engineering :: Visualization
Requires-Dist: bokeh (>=2.4.3,<3.0.0)
Requires-Dist: pandas (>=1.4.1,<2.0.0)
Requires-Dist: panel (>=0.13.1,<0.14.0)
Requires-Dist: wordcloud (>=1.8.2.2,<2.0.0.0)
